gitenvy/__init__.py
gitenvy/cli.py
gitenvy/config_manager.py
gitenvy/crypto.py
gitenvy/env_manager.py
gitenvy/utils/config_builder.py
gitenvy/utils/helper.py
gitenvy-1.3.1.dist-info/entry_points.txt
gitenvy-1.3.1.dist-info/licenses/LICENSE
gitenvy-1.3.1.dist-info/METADATA
gitenvy-1.3.1.dist-info/WHEEL
gitenvy-1.3.1.dist-info/RECORD
